setup.py
pts_distribution/Binomialdistribution.py
pts_distribution/Gaussiandistribution.py
pts_distribution/Generaldistribution.py
pts_distribution/__init__.py
pts_distribution.egg-info/PKG-INFO
pts_distribution.egg-info/SOURCES.txt
pts_distribution.egg-info/dependency_links.txt
pts_distribution.egg-info/not-zip-safe
pts_distribution.egg-info/top_level.txt